anamnesisai/__init__.py
anamnesisai/config.py
anamnesisai/core.py
anamnesisai/generation.py
anamnesisai/py.typed
anamnesisai/supported_fhir.py
anamnesisai/templates/allergy.json
anamnesisai/templates/careplan.json
anamnesisai/templates/condition.json
anamnesisai/templates/diagnostic_report.json
anamnesisai/templates/encounter.json
anamnesisai/templates/medication_request.json
anamnesisai/templates/observation.json
anamnesisai/templates/patients.json
anamnesisai/templates/practitioner.json
anamnesisai/templates/procedure.json
anamnesisai/utils.py
anamnesisai-0.4.0.dist-info/LICENSE
anamnesisai-0.4.0.dist-info/METADATA
anamnesisai-0.4.0.dist-info/WHEEL
anamnesisai-0.4.0.dist-info/RECORD
